gooey_ui/__init__.py
gooey_ui/components.py
gooey_ui/pubsub.py
gooey_ui/state.py
gooey_ui-0.1.0.dist-info/METADATA
gooey_ui-0.1.0.dist-info/WHEEL
gooey_ui-0.1.0.dist-info/RECORD
