Metadata-Version: 2.1
Name: gooey-ui
Version: 0.1.0
Summary: 
Author: Dev Aggarwal
Author-email: devxpy@gmail.com
Requires-Python: >=3.10,<4.0
Classifier: Programming Language :: Python :: 3
Classifier: Programming Language :: Python :: 3.10
Classifier: Programming Language :: Python :: 3.11
Requires-Dist: fastapi (>=0.85.2,<0.86.0)
Requires-Dist: furl (>=2.1.3,<3.0.0)
Requires-Dist: pydantic (>=1.10.12,<2.0.0)
Requires-Dist: python-multipart (>=0.0.6,<0.0.7)
Requires-Dist: redis (>=4.5.1,<5.0.0)
Requires-Dist: uvicorn[standard] (>=0.18.3,<0.19.0)
